netcook_v2/__init__.py
netcook_v2/netcook.py
netcook_v2-2.6.dist-info/METADATA
netcook_v2-2.6.dist-info/WHEEL
netcook_v2-2.6.dist-info/entry_points.txt
netcook_v2-2.6.dist-info/top_level.txt
netcook_v2-2.6.dist-info/RECORD
